LICENSE
README.md
setup.py
src/human_cver/__init__.py
src/human_cver.egg-info/PKG-INFO
src/human_cver.egg-info/SOURCES.txt
src/human_cver.egg-info/dependency_links.txt
src/human_cver.egg-info/entry_points.txt
src/human_cver.egg-info/requires.txt
src/human_cver.egg-info/top_level.txt
src/human_cver/datasets/__init__.py
src/human_cver/datasets/base.py
src/human_cver/datasets/image_folder.py
src/human_cver/datasets/mixed_dataset.py
src/human_cver/datasets/split_dataset.py
src/human_cver/datasets/video.py
src/human_cver/datasets/Pose2Mesh/__init__.py
src/human_cver/datasets/Pose2Mesh/pw3d.py
src/human_cver/datasets/Pose2Mesh/Human36M/__init__.py
src/human_cver/datasets/Pose2Mesh/Human36M/dataset.py
src/human_cver/datasets/Pose2Mesh/Human36M/noise_stats.py
src/human_cver/geometric/__init__.py
src/human_cver/geometric/coord.py
src/human_cver/image/__init__.py
src/human_cver/image/convert.py
src/human_cver/image/image_ops.py
src/human_cver/io/__init__.py
src/human_cver/io/io.py
src/human_cver/io/obj_file.py
src/human_cver/io/tsv_file.py
src/human_cver/metric/__init__.py
src/human_cver/metric/keypoint_loss.py
src/human_cver/metric/mpjpe_torch.py
src/human_cver/metric/pampjpe.py
src/human_cver/models/__init__.py
src/human_cver/models/mine_transformer.py
src/human_cver/models/transformer.py
src/human_cver/models/smpl/J_regressor_coco.npy
src/human_cver/models/smpl/J_regressor_extra.npy
src/human_cver/models/smpl/J_regressor_h36m_correct.npy
src/human_cver/models/smpl/__init__.py
src/human_cver/models/smpl/kp_map.py
src/human_cver/models/smpl/kp_utils.py
src/human_cver/models/smpl/smpl.py
src/human_cver/tools/__init__.py
src/human_cver/tools/conda.py
src/human_cver/tools/downloader.py
src/human_cver/tools/geometric.py
src/human_cver/tools/logger.py
src/human_cver/tools/md5sum.py
src/human_cver/tools/rsync.py
src/human_cver/tools/system_info.py
src/human_cver/tools/tasks.py
src/human_cver/tools/time.py
src/human_cver/tools/timer.py
src/human_cver/tools/wrap.py
src/human_cver/tracker/__init__.py
src/human_cver/tracker/analyzer.py
src/human_cver/tracker/track_base.py
src/human_cver/tracker/track_image.py
src/human_cver/tracker/track_number.py
src/human_cver/tracker/track_numpy.py
