Metadata-Version: 2.1
Name: human-cver
Version: 1.0.1
Summary: A small example package
Home-page: https://github.com/wkailiu/human_cver
Author: Wenkai Liu
Author-email: wenkai_liu@hust.edu.cn
License: UNKNOWN
Project-URL: Bug Tracker, https://github.com/wkailiu/human_cver/issues
Platform: UNKNOWN
Classifier: Programming Language :: Python :: 3
Classifier: License :: OSI Approved :: MIT License
Classifier: Operating System :: OS Independent
Requires-Python: >=3.6
License-File: LICENSE
